traia_iatp/README.md
traia_iatp/X509-cert-2235240396129682827.pem
traia_iatp/__init__.py
traia_iatp/preview_diagrams.html
traia_iatp/cli/__init__.py
traia_iatp/cli/main.py
traia_iatp/client/__init__.py
traia_iatp/client/a2a_client.py
traia_iatp/client/crewai_a2a_tools.py
traia_iatp/client/d402_a2a_client.py
traia_iatp/client/grpc_a2a_tools.py
traia_iatp/client/root_path_a2a_client.py
traia_iatp/contracts/__init__.py
traia_iatp/contracts/iatp_contracts_config.py
traia_iatp/contracts/wallet_creator.py
traia_iatp/contracts/data/abis/contract-abis-arbitrum_one.json
traia_iatp/contracts/data/abis/contract-abis-localhost.json
traia_iatp/contracts/data/abis/contract-abis-sepolia.json
traia_iatp/contracts/data/addresses/contract-addresses.json
traia_iatp/contracts/data/addresses/contract-proxies.json
traia_iatp/core/__init__.py
traia_iatp/core/models.py
traia_iatp/d402/MIDDLEWARE_ARCHITECTURE.md
traia_iatp/d402/PRICE_BUILDER_USAGE.md
traia_iatp/d402/README.md
traia_iatp/d402/__init__.py
traia_iatp/d402/asgi_wrapper.py
traia_iatp/d402/chains.py
traia_iatp/d402/client.py
traia_iatp/d402/common.py
traia_iatp/d402/encoding.py
traia_iatp/d402/facilitator.py
traia_iatp/d402/mcp_middleware.py
traia_iatp/d402/models.py
traia_iatp/d402/networks.py
traia_iatp/d402/path.py
traia_iatp/d402/payment_introspection.py
traia_iatp/d402/payment_signing.py
traia_iatp/d402/price_builder.py
traia_iatp/d402/starlette_middleware.py
traia_iatp/d402/types.py
traia_iatp/d402/clients/__init__.py
traia_iatp/d402/clients/base.py
traia_iatp/d402/clients/httpx.py
traia_iatp/d402/examples/client_example.py
traia_iatp/d402/examples/server_example.py
traia_iatp/d402/servers/__init__.py
traia_iatp/d402/servers/base.py
traia_iatp/d402/servers/example_general_server.py
traia_iatp/d402/servers/fastapi.py
traia_iatp/d402/servers/mcp.py
traia_iatp/d402/servers/starlette.py
traia_iatp/mcp/D402_MCP_ADAPTER_FLOW.md
traia_iatp/mcp/__init__.py
traia_iatp/mcp/client.py
traia_iatp/mcp/d402_mcp_tool_adapter.py
traia_iatp-0.1.79.dist-info/licenses/LICENSE
traia_iatp-0.1.79.dist-info/METADATA
traia_iatp-0.1.79.dist-info/WHEEL
traia_iatp-0.1.79.dist-info/entry_points.txt
traia_iatp-0.1.79.dist-info/top_level.txt
traia_iatp-0.1.79.dist-info/RECORD
