Metadata-Version: 2.4
Name: traia-iatp
Version: 0.1.79
Summary: Inter-Agent Transfer Protocol (IATP) - Enable AI Agents to utilize other AI Agents as tools
Project-URL: Documentation, https://docs.d402.net
Project-URL: Source, https://github.com/Traia-IO/IATP
Keywords: crewai,iatp,agent-to-agent,a2a,mcp,web3,cryptocurrency,tools
Classifier: Programming Language :: Python :: 3
Classifier: Operating System :: OS Independent
Requires-Python: >=3.12
License-File: LICENSE
Requires-Dist: a2a-sdk>=0.3.19
Requires-Dist: aiohttp>=3.12.13
Requires-Dist: anyio>=4.0.0
Requires-Dist: crewai>=0.203.1
Requires-Dist: crewai-tools[mcp]>=0.76.0
Requires-Dist: docker>=7.1.0
Requires-Dist: fastapi>=0.119.0
Requires-Dist: httpx[http2]>=0.28.1
Requires-Dist: jinja2>=3.1.6
Requires-Dist: mcp>=1.1.2
Requires-Dist: nest-asyncio>=1.6.0
Requires-Dist: openai>=1.109.1
Requires-Dist: pydantic>=2.12.2
Requires-Dist: pymongo[aws]>=4.13.0
Requires-Dist: python-dotenv>=1.1.1
Requires-Dist: pytz>=2025.2
Requires-Dist: requests>=2.32.5
Requires-Dist: rich>=14.2.0
Requires-Dist: starlette>=0.45.0
Requires-Dist: tomli>=2.0.0
Requires-Dist: typer>=0.19.2
Requires-Dist: uvicorn>=0.37.0
Requires-Dist: agentops>=0.4.21
Requires-Dist: dnspython==2.6.1
Requires-Dist: eth-account>=0.11.0
Requires-Dist: web3>=6.15.0
Provides-Extra: dev
Requires-Dist: pytest>=8.4.2; extra == "dev"
Requires-Dist: pytest-cov>=4.0.0; extra == "dev"
Requires-Dist: black>=23.0.0; extra == "dev"
Requires-Dist: flake8>=6.0.0; extra == "dev"
Requires-Dist: mypy>=1.0.0; extra == "dev"
Requires-Dist: pre-commit>=3.0.0; extra == "dev"
Provides-Extra: publish
Requires-Dist: wheel; extra == "publish"
Requires-Dist: twine; extra == "publish"
Requires-Dist: build; extra == "publish"
Dynamic: license-file
